cbmpy/CBCPLEX.py
cbmpy/CBCommon.py
cbmpy/CBConfig.py
cbmpy/CBDataStruct.py
cbmpy/CBDefaultModels.py
cbmpy/CBGLPK.py
cbmpy/CBGLPKOLD.py
cbmpy/CBGUI.py
cbmpy/CBModel.py
cbmpy/CBModelTools.py
cbmpy/CBMultiCore.py
cbmpy/CBMultiEnv.py
cbmpy/CBMultiModel.py
cbmpy/CBNetDB.py
cbmpy/CBPlot.py
cbmpy/CBQt4.py
cbmpy/CBRead.py
cbmpy/CBReadtxt.py
cbmpy/CBSandBox.py
cbmpy/CBSolve.py
cbmpy/CBSolver.py
cbmpy/CBSolverX.py
cbmpy/CBTools.py
cbmpy/CBWrite.py
cbmpy/CBWx.py
cbmpy/CBXML.py
cbmpy/PyscesSED.py
cbmpy/PyscesStoich.py
cbmpy/__init__.py
cbmpy/_multicoreenvfva.py
cbmpy/_multicorefva.py
cbmpy/_qtloader.py
cbmpy/miriamids.py
cbmpy/fluxmodules/TestDecomposition.py
cbmpy/fluxmodules/TestEnumerate.py
cbmpy/fluxmodules/TestFluxModules.py
cbmpy/fluxmodules/TestMatroid.py
cbmpy/fluxmodules/TestSparseRationals.py
cbmpy/fluxmodules/__init__.py
cbmpy/fluxmodules/decomposition.py
cbmpy/fluxmodules/enumerate.py
cbmpy/fluxmodules/fluxmodules.py
cbmpy/fluxmodules/matroid.py
cbmpy/fluxmodules/random_color.py
cbmpy/fluxmodules/sparserationals.py
cbmpy-0.8.8.1.dist-info/LICENCE_GPLv3.txt
cbmpy-0.8.8.1.dist-info/METADATA
cbmpy-0.8.8.1.dist-info/WHEEL
cbmpy-0.8.8.1.dist-info/top_level.txt
cbmpy-0.8.8.1.dist-info/RECORD
